LICENSE
LICENSE.txt
README.rst
setup.cfg
setup.py
THJPpython/__init__.py
THJPpython/iampython.py
THJPpython.egg-info/PKG-INFO
THJPpython.egg-info/SOURCES.txt
THJPpython.egg-info/dependency_links.txt
THJPpython.egg-info/top_level.txt