Metadata-Version: 2.1
Name: THJPpython
Version: 0.0.1
Summary: Who is Mon THJP
Home-page: https://github.com/amonTHJP
Download-URL: https://github.com/amonTHJP
Author: Mon THJP
Author-email: amonprograms@gmail.com
License: MIT
Keywords: Mon THJP,ASCII ART
Classifier: Development Status :: 3 - Alpha
Classifier: Intended Audience :: Education
Classifier: Topic :: Utilities
Classifier: License :: OSI Approved :: MIT License
Classifier: Programming Language :: Python :: 3
Classifier: Programming Language :: Python :: 3.4
Classifier: Programming Language :: Python :: 3.5
Classifier: Programming Language :: Python :: 3.6
Classifier: Programming Language :: Python :: 3.7
Classifier: Programming Language :: Python :: 3.8
Classifier: Programming Language :: Python :: 3.9
Classifier: Programming Language :: Python :: 3.10
License-File: LICENSE
License-File: LICENSE.txt
